tf_sentencepiece/__init__.py
tf_sentencepiece/_sentencepiece_processor_ops.so.1.15.0
tf_sentencepiece/_sentencepiece_processor_ops.so.1.15.2
tf_sentencepiece/_sentencepiece_processor_ops.so.2.0.0
tf_sentencepiece/_sentencepiece_processor_ops.so.2.0.1
tf_sentencepiece/_sentencepiece_processor_ops.so.2.1.0
tf_sentencepiece/_sentencepiece_processor_ops.so.2.2.0
tf_sentencepiece/sentencepiece_processor_ops.py
tf_sentencepiece-0.1.92.dist-info/METADATA
tf_sentencepiece-0.1.92.dist-info/WHEEL
tf_sentencepiece-0.1.92.dist-info/top_level.txt
tf_sentencepiece-0.1.92.dist-info/RECORD
