Metadata-Version: 2.1
Name: tf-sentencepiece
Version: 0.1.92
Summary: SentencePiece Encode/Decode ops for TensorFlow
Home-page: https://github.com/google/sentencepiece
Author: Taku Kudo
Author-email: taku@google.com
License: Apache
Keywords: tensorflow machine learning sentencepiece NLP segmentation
Platform: Unix
Classifier: Development Status :: 5 - Production/Stable
Classifier: Environment :: Console
Classifier: Intended Audience :: Developers
Classifier: Intended Audience :: Science/Research
Classifier: License :: OSI Approved :: Apache Software License
Classifier: Operating System :: Unix
Classifier: Programming Language :: Python
Classifier: Topic :: Text Processing :: Linguistic
Classifier: Topic :: Software Development :: Libraries :: Python Modules
